simple_db/__init__.py
simple_db/db.py
simple_db-1.0.dist-info/LICENSE
simple_db-1.0.dist-info/METADATA
simple_db-1.0.dist-info/WHEEL
simple_db-1.0.dist-info/top_level.txt
simple_db-1.0.dist-info/RECORD
